Metadata-Version: 2.1
Name: weighted-collection
Version: 1
Summary: A WeightedCollection assigns probability weights per elements and returns elements randomly using those weights.
Home-page: https://github.com/subalterngames/weighted_collection
Author: Seth Alter
Author-email: subalterngames@gmail.com
License: MIT
Download-URL: https://github.com/subalterngames/weighted_collection/archive/v1.0.tar.gz
Keywords: collection,random
Platform: UNKNOWN
Classifier: Development Status :: 5 - Production/Stable
Classifier: Intended Audience :: Developers
Classifier: Topic :: Software Development
Classifier: License :: OSI Approved :: MIT License
Classifier: Programming Language :: Python :: 3.6
Classifier: Programming Language :: Python :: 3.7
Classifier: Programming Language :: Python :: 3.8
